python_benchmark_thread_vs_process/__init__.py
python_benchmark_thread_vs_process/cpuinfo.py
python_benchmark_thread_vs_process/main.py
python_benchmark_thread_vs_process/multi_process.py
python_benchmark_thread_vs_process/multi_thread.py
python_benchmark_thread_vs_process/operation.py
python_benchmark_thread_vs_process-0.1.5.dist-info/METADATA
python_benchmark_thread_vs_process-0.1.5.dist-info/WHEEL
python_benchmark_thread_vs_process-0.1.5.dist-info/entry_points.txt
python_benchmark_thread_vs_process-0.1.5.dist-info/top_level.txt
python_benchmark_thread_vs_process-0.1.5.dist-info/RECORD
