Metadata-Version: 2.1
Name: python-benchmark-thread-vs-process
Version: 0.1.5
Summary: Python Benchmark: multi-thread vs multi-process
Home-page: https://github.com/minhng-info/python-benchmark-thread-vs-process
Author: minhng-info
Author-email: minhng92@gmail.com
Maintainer: minhng-info
Maintainer-email: minhng92@gmail.com
License: MIT
Download-URL: https://github.com/minhng-info/python-benchmark-thread-vs-process/tarball/master
Platform: UNKNOWN
Classifier: Development Status :: 4 - Beta
Classifier: License :: OSI Approved :: MIT License
Classifier: Topic :: Software Development :: Libraries :: Python Modules
Classifier: Intended Audience :: Developers
Classifier: Programming Language :: Python :: 3
Classifier: Programming Language :: Python :: 3.5
Classifier: Programming Language :: Python :: 3.6
Classifier: Programming Language :: Python :: 3.7
Classifier: Programming Language :: Python :: 3.8
Classifier: Programming Language :: Python :: 3.9
Classifier: Programming Language :: Python :: Implementation
Requires-Python: <4,>3.5
Requires-Dist: psutil (==5.7.0)
Requires-Dist: terminaltables (==3.1.0)
